basic_math/__init__.py
basic_math_fuad-1.0.0.dist-info/METADATA
basic_math_fuad-1.0.0.dist-info/WHEEL
basic_math_fuad-1.0.0.dist-info/top_level.txt
basic_math_fuad-1.0.0.dist-info/RECORD
